Metadata-Version: 2.1
Name: jupyter-mdk
Version: 0.1.1
Summary: Jupyter Model Development Kit
Home-page: https://github.com/Open-MBEE/jupyter-mdk
Author-email: 
License: Apache 2.0
Keywords: MDK,Jupyter,MMS
Platform: UNKNOWN
